Workbook
Name BKL.Beschreibung: Tabelle1!$C$128:$G$151
Name Gutachten: Beseitigungskosten!$C$63
Name Jürgen: Tabelle1!$C$130:$G$151
Name Kinderspielhaus: 'Anl IV Schuppen'!$B$137
Name nelke: Tabelle1!$B$3:$F$83
Name rose: Tabelle1!$B$129:$G$151
Name typen: Baulichkeiten!$N$45:$N$66
Name ungeprüft: Tabelle1!$I$12
Name uwe: Tabelle1!$J$54:$N$75
Name uwe.2: Tabelle1!$J$54:$N$75
Name wasserlos: Beseitigungskosten!$C$67

Sheet Formalien
A1: Formalien | G1: Seite 1
B3: Kleingartenanlage | E3: KGA Musterwiese | H3: Hinweise zur Anwendung der Wertermittlung komplett
B4: Parzelle | E4: 42
B5: ggf.Weg soweit erforderlich | H5: für den Wertermittler Bau
B6: Unterpächter | E6: Erika Musterfrau | H6: wir. | I6: Erst die Formalien ausfüllen | N6: Register rot
B7: Auftraggeber | H7: wir. | I7: Dann Anlage 1 | N7: Register grün
C8: vertreten durch Rechtsanwalt | H8: wir. | I8: dann nur die Anlage 4 Seite 1 | N8: Register gelb
B9: anwesend | C9: für den Verein | I9: Angaben werden auf Register Schuppen und Dach übertragen | N9: Register hell lila
C10: für den Unterpächter | H10: wir. | I10: Ausdrucken nach Bedarf | N10: normal oder
C11: für den Auftraggeber | N11: Dach oder
B12: Wertermittler: Baulichkeiten | N12: Schuppen
B13: Wertermittler: Außenanlagen & Aufwuchs
B14: Wertermittlung am: | H14: für den Wertermittler Außenanlagen/Grün
B15: Protokollerstellung am: | H15: wir | I15: Erst die Formalien ausfüllen | N15: Register rot
B16: Parzellenfläche lt. Vertrag | E16: 300 | F16: m² | H16: wir | I16: Dann Anlage Außenanlagen, Aufwuchs 2 ggf. Aufwuchs 3 | N16: Register blau
B17: Vorgangs-Nr.: | E17: 2026-602 | H17: wir | I17: dann Anlage 4 Beseitigungskosten Seite 1 und 2 | N17: Register gelb
J18: Angaben werden auf Register Schuppen und Dach übertragen
H19: wir | I19: Ausdrucken nach Bedarf | N19: normal oder
B20: BT: Ü = überdachter Laubenvorplatz / BT: LVP = Laubenvorplatz ohne Überdachung | N20: Dach oder
B21: BT: GWH = Gewächshaus | N21: Schuppen
B22: BT: S oder U = Schuppen/Blechschuppen, Unterstand, Bkl. I bis IV.
B23: BT: A1 bis z.B. A4, Anbau Laube oder Laubenerweiterung | H23: Die Blätter sind geschützt, so dass nur die benötigten Zellen und Flächen genutzt werden können.
H24: Der Blattschutz kann über
I25: Start > Format > Schutz > Blattschutz aufheben/Blatt schützen
H26: aufgehoben und wieder in Kraft gesetzt werden. Ausgenommen ist das Register "Tabelle 1"
H27: das Passwort geschützt ist.

Sheet Deckbl UPV 
A1: Bezirksverband der Gartenfreunde Pankow e.V.
A2: Quickborner Str. 12, 13158 Berlin, info@gartenfreunde-pankow.de
A4: Wertermittlung bei Unterpächterwechsel
A7: Name des Unterpächters: | C7: =Formalien!$E$6
A8: Kleingartenanlage: | C8: =Formalien!$E$3
A9: Parzelle / Weg: | C9: =IF(Formalien!$E$5="",Formalien!$E$4,Formalien!$E$4&" / "&Formalien!$E$5)
A10: Vorgangs-Nr.: | C10: =Formalien!$E$17
A11: Wertermittlung am: | C11: =Formalien!$E$14
A13: Anwesend waren: | B13: Wertermittler Bau: | E13: =Formalien!$E$12
B14: Wertermittler Außenanlagen und Aufwuchs: | E14: =Formalien!$E$13
B15: für den Unterpächter: | E15: =Formalien!$E$10
B16: für den Auftraggeber: | E16: =Formalien!$E$11
B17: für den Verein: | E17: =Formalien!$E$9
A19: Bewertung
B21: Baulichkeiten lt. Anlage 1 | E21: =Baulichkeiten!$K$81 | F21: (einschließlich Abwasseranlage)
B22: Außenanlagen lt. Anlage 2 | E22: =Außenanlagen!$L$46
B23: Aufwuchs lt. Anlage 3 | E23: =MAX('Aufwuchs I'!L46,'Aufwuchs II'!L46)
B24: Zwischensumme | E24: =SUM(E21:E23)
B25: Kosten nicht beräumter Baulichkeiten | E25: =Baulichkeiten!$H$104
B26: Beseitigungskosten Bau lt. Anlage 4 | E26: =Beseitigungskosten!$K$24
B27: Beseitigungskosten AA & Aufwuchs lt. Anlage 4 | E27: =Beseitigungskosten!$K$45
B28: Gesamtbetrag mit Abzügen | E28: =SUM(E24-E25-E26-E27)
A31: Die Wertermittlung erfolgt auf der Grundlage der "Wertermittlungsrichtlinie für Kleingärten" des Landesverbandes Berlin der Gartenfreunde e.V.
A33: Erklärung: Die Wertermittler haften nicht für versteckte Mängel. Versteckte Mängel im Sinne dieses Protokolls sind Mängel an Baulichkeiten und baulichen Anlagen, die vom Wertermittler nicht eingesehen werden konnten. Dabei ist es unwichtig, ob die Einsichtbarkeit wegen Wandverkleidungen innen und/oder außen (mit oder ohne Baugenehmigung), dichtem Pflanzenwuchs, eingebautem Mobiliar oder sonstigen Gegenständen behindert wurde.
A34: Dieses Protokoll ist das Ergebnis einer Momentaufnahme von Daten zum Zeitpunkt der Wertermittlung auf der Parzelle. Es ist rechtlich nicht mit einem Gutachten gleichzusetzen. Widersprüche wegen nicht korrekter Aufnahme von Daten sind innerhalb 14 Tage direkt an die Wertermittler in schriftlicher Form zu richten. Ein Rechtsanspruch auf Änderung des Protokolls besteht nicht, wenn zum Zeitpunkt der Wertermittlung nicht alle Dokumente zur Ermittlung der Rechtmäßigkeit der Errichtung von Baulichkeiten und Außenanlagen vorgelegt wurden. Besteht trotzdem der dringende Wunsch des abgebenden Unterpächters das Protokoll nachträglich zu ändern, z.B. wegen nachträglicher Einreichung von Nachweisen, können Kosten entstehen.
A35: Änderungen der Bewertung durch nachträgliche Prüfung der Vertragslage sind nicht Bestandteil dieses Protokolls und bedürfen einer zusätzlichen Dokumentation.
A36: Der neue Unterpächter muss das Inventar nicht übernehmen, es muss dann vom scheidenden Unterpächter entfernt werden.
A37: Wir weisen Sie darauf hin, dass die durch die Wertermittler ermittelten Beträge erst bei Neuverpachtung zur Zahlung fällig werden (siehe § 9 Abs. 7 des Unterpachtvertrages).
A38: Ein etwaiger Widerspruch gegen diese Wertermittlung ist innerhalb von 14 Tagen schriftlich an den Bezirksverband der Gartenfreunde Pankow e.V. zu richten.
A40: Kontakt: wertermittlung@gartenfreunde-pankow.de
A43: Datum: | D43: Unterschrift BV
G44: Seite 1
A45: „Sachlich und rechnerisch geprüft “

Sheet Baulichkeiten
A1: Anlage 1 (Blatt 1) – Bewertung Baulichkeiten
A2: Kleingartenanlage: | D2: =Formalien!$E$3 | H2: Parzelle: | I2: =Formalien!$E$4
A3: Parzellenfläche lt. Vertrag: | E3: =Formalien!$E$16 | F3: m² | I3: =Formalien!$E$5
A4: Name des Unterpächters: | E4: =Formalien!$E$6
A7: Der Berechnung zugrunde gelegter Baupreisindex (2015 = 100): | H7: 179.2 | I7: für 2026
A8: Hinweise: | C8: BT | D8: = Bauteil
C9: NHK/m² | D9: = Normalherstellungskosten pro m²
C10: Altersabzug | D10: =Alterswertminderung entsprechend der Abzugstabelle für Abschreibungen in den einzelnen Bauklassen
A11: 1. Laube
A12: BT: | B12: L | E12: Bauklasse: | F12: =Tabelle1!$D$88 | G12: fehlt
B13: Baujahr: | H13: Restnutzungsjahre:
B14: NHK/m²: | C14: =Tabelle1!$B$90 | D14: abzüglich | F14: % Mängelabzug = | H14: =ROUND(C14-C14*E14/100,2)
C15: =$H$14 | D15: abzüglich | E15: =Tabelle1!$I$90 | F15: % Altersabzug = | H15: =ROUND(C15-C15*E15%,2) | M15: Bauklasse | N15: BKL.Beschreibung | P15: NHK/m²
C16: =$H$15 | D16: x | E16: =H7/100 | F16: (1/100 Baupreisindex) = | H16: =ROUND(C16*E16,2) | M16: I | N16: I
B17: m² *) X | C17: =$H$16 | D17: = | E17: =ROUND(A17*C17,2) | I17: Wert BT | J17: =$B$12 | K17: =E17 | M17: I.1 | N17: =N45 -> Stein 17,50 - 23,99 cm | P17: 515
A18: *) zulässig überbaute Fläche (siehe Massenberechnung) | M18: I.2 | N18: =N46 | P18: 595
A19: BT: | B19: L | C19: nicht berechnete Baufläche | J19: m² | M19: I.3 | N19: =N47 | P19: 704
M20: II | N20: II
A21: BT: | B21: A1 | E21: Bauklasse: | F21: =Tabelle1!$D$93 | G21: fehlt | M21: II.1 | N21: =N48 | P21: 350
B22: Baujahr: | H22: Restnutzungsjahre: | M22: II.3 | N22: =N49 | P22: 490
B23: NHK/m²: | C23: =Tabelle1!$B$95 | D23: abzüglich | F23: % Mängelabzug = | H23: =ROUND(C23-C23*E23/100,2) | M23: III | N23: III
C24: =$H$23 | D24: abzüglich | E24: =Tabelle1!$I$95 | F24: % Altersabzug = | H24: =ROUND(C24-C24*E24%,2) | M24: III.1 | N24: =N50 | P24: 420
C25: =$H$24 | D25: x | E25: =H7/100 | F25: (1/100 Baupreisindex) = | H25: =ROUND(C25*E25,2) | M25: III.2 | N25: =N51 | P25: 555
B26: m² *) X | C26: =$H$25 | D26: = | E26: =ROUND(A26*C26,2) | I26: Wert BT | J26: =$B$21 | K26: =E26 | M26: III.3 | N26: =N52 -> Blockhaus ab 9,0 cm | P26: 672
A27: *) zulässig überbaute Fläche (siehe Massenberechnung) | M27: III.1 | N27: =N53 | P27: 420
A28: BT: | B28: A1 | C28: nicht berechnete Baufläche, Laube > als 24,0 m² | J28: m² | M28: III.2 | N28: =N54 -> Doppelt Holz 15,00 - 19,99 cm | P28: 555
M29: III.3 | N29: =N55 | P29: 672
A30: BT: | B30: A2 | E30: Bauklasse: | F30: =Tabelle1!$D$98 | G30: fehlt | M30: IV | N30: IV
B31: Baujahr: | H31: Restnutzungsjahre: | M31: IV.1 | N31: =N58 -> Blockhaus bis 3,00 cm | P31: 265
B32: NHK/m²: | C32: =Tabelle1!$B$100 | D32: abzüglich | F32: % Mängelabzug = | H32: =ROUND(C32-C32*E32/100,2) | M32: IV.2 | N32: =N61 | P32: 325
C33: =$H$32 | D33: abzüglich | E33: =Tabelle1!$I$100 | F33: % Altersabzug = | H33: =ROUND(C33-C33*E33%,2) | M33: IV.3 | N33: =N62 | P33: 420
C34: =$H$33 | D34: x | E34: =$E$16 | F34: (1/100 Baupreisindex) = | H34: =ROUND(C34*E34,2) | M34: IV.1 | N34: =N63 | P34: 265
B35: m² *) X | C35: =$H$34 | D35: = | E35: =ROUND(A35*C35,2) | I35: Wert BT | J35: =$B$30 | K35: =E35 | M35: IV.3 | N35: =N65 | P35: 420
A36: *) zulässig überbaute Fläche (siehe Massenberechnung)
A37: BT: | B37: A2 | C37: nicht berechnete Baufläche | J37: m²
B38: nicht berechnete Bauflächen von BT: | I38: =I19+I28+I37 | J38: m²
A39: 2. Sonstige bauliche Anlagen (Gewächshaus, separatstehende Baulichkeiten und offener Laubenvorplatz)
A40: 2.1.Gewächshaus BT: | D40: GWH | E40: Altersminderung/Jahr: | H40: % Alter ca.:
C41: NHK/m² | E41: abzüglich | F41: 0 | G41: Mängel | H41: = | I41: =ROUND(D41-D41*F41,2)
C42: =I41 | D42: abzüglich | E42: =I40*G40 | F42: % Altersabzug | H42: 5 | I42: =IF(E42>99,"abgeschrieben",ROUND(C42-C42*E42%,2))
C43: =IF(I42="abgeschrieben",0,I42) | D43: x | E43: =H7/100 | F43: (1/100 Baupreisindex) | H43: = | I43: =ROUND(C43*E43,2)
A44: zulässig überbaute Fläche (s. Massenberechnung) | G44: m² x | H44: =I43 | I44: = Wert BT | J44: =$D$40 | K44: =ROUND(F44*H44,2) | N44: Typen
N45: =Tabelle1!J87 -> Stein 17,50 - 23,99 cm | P45: Lebenserwartung
A46: 2.2. zul. einzelne Schuppen u.ä. | N46: =Tabelle1!J88 | P46: 33 Jahre 3% | R46: 3
A47: BT: | B47: S oder U | E47: Bauklasse: | F47: =Tabelle1!$D$103 | G47: fehlt | N47: =Tabelle1!J89 | P47: 25 Jahre 4% | R47: 4
B48: Baujahr: | H48: Restnutzungsjahre: | N48: =Tabelle1!J90 | P48: 20 Jahre 5% Regelwert | R48: 5
B49: NHK/m²: | C49: =Tabelle1!$B$105 | D49: abzüglich | F49: % Mängelabzug = | H49: =ROUND(C49-C49*E49/100,2) | N49: =Tabelle1!J91 | P49: 15 Jahre 7% | R49: 7
C50: =H49 | D50: abzüglich | E50: =Tabelle1!$I$105 | F50: % Altersabzug = | H50: =ROUND(C50-C50*E50%,2) | N50: =Tabelle1!J92 | P50: 10 Jahre 10% | R50: 10
C51: =H50 | D51: x | E51: =H7/100 | F51: (1/100 Baupreisindex) = | H51: =ROUND(C51*E51,2) | N51: =Tabelle1!J93
B52: m² *) X | C52: =$H$51 | D52: = | E52: =ROUND(A52*C52,2) | I52: Wert BT | J52: =$B$47 | K52: =E52 | N52: =Tabelle1!J94 -> Blockhaus ab 9,0 cm
A53: *) zulässig überbaute Fläche (siehe Massenberechnung) | I53: Zwischensumme | K53: =SUM(K14:K52) | N53: =Tabelle1!J95
K54: Seite 2 | N54: =Tabelle1!J96 -> Doppelt Holz 15,00 - 19,99 cm
A55: Anlage 1 (Blatt 2) – Bewertung von Baulichkeiten | N55: =Tabelle1!J97
A56: Kleingartenanlage: | D56: =Formalien!$E$3 | H56: Parz.Nr.: | I56: =Formalien!$E$4
A57: Parzellenfläche lt. Vertrag: | D57: =Formalien!$E$16 | E57: m²
A58: Name des Unterpächters: | D58: =Formalien!$E$6 | N58: =Tabelle1!J98 -> Blockhaus bis 3,00 cm
I61: Übertrag: | K61: =K53 | N61: =Tabelle1!J99
A62: 2.3. Überdachter Laubenvorplatz | E62: BT: | F62: Ü1 | L62: Hinweis: Beim Laubenvorplatz immer darauf achten, dass unter E58 bzw. B62 bei einem Anfalll von a) oder b) beim anderen Bauteil 0 bzw. ohne (siehe dropdown-Listen) eingetragen ist. | N62: =Tabelle1!J100
A63: a) integriert | D63: NHK/m² | E63: 0 | F63: abzüglich | G63: =IF(E63>0,E14,0) | H63: % Mängel = | I63: =ROUND(E63-E63*G63%,2) | N63: =Tabelle1!J101
C64: =I63 | D64: abzüglich | E64: =IF(C64>0,E15,0) | F64: % Altersabzug wie Laube = | I64: =ROUND(C64-C64*E64%,2) | N64: =Tabelle1!J102 -> Doppelwand 4,01 - 8,00 cm
N65: =Tabelle1!J103
A66: b) angebaut | C66: Altersminderung pro Jahr: | F66: % Alter ca.: | H66: 0 | I66: Jahre | N66: =Tabelle1!J104
A67: Güte: | B67: ohne | D67: NHK/m² | E67: =IF(B67=N67,O67,IF(B67=N68,O68,IF(B67=N70,O70))) | F67: abzüglich | G67: 0 | H67: Mängel = | I67: =ROUND(E67-E67*G67,2) | N67: hochwertig | O67: 175
D68: =I67 | E68: abzüglich | G68: 100 | H68: Altersabzug = | I68: =ROUND(D68-D68*G68%,2) | N68: minderwertig | O68: 80
C70: =IF(I68=0,I64,I68) | E70: =$H$7/100 | F70: (1/100 Baupreisindex) | H70: = | I70: =ROUND(C70*E70,2) | N70: ohne
A71: zulässig überbaute Fläche (s. Massenberechnung) | F71: 0 | G71: m² x | H71: =I70 | I71: = | K71: =ROUND(F71*H71,2)
A72: 3. Abwasser
A73: 3.1. | B73: Abwassersammelgrube Genehmigung vom | H73: ggf.Nr:
B74: Alter | D74: ( ) Jahre alt | E74: Grundwert | F74: 470 | H74: /m³
B75: ./. | C75: =C74*3 | D75: % Altersabzug (3%/Jahr) = | F75: =ROUND(F74-F74*C75/100,2) | H75: /m³ x | J75: m³ = | K75: =IF(E76 ="fehlt",0,ROUND(F75*I75,2))
A76: Dichtheitsgutachten vom | N76: fehlt
D77: Abzug wegen nicht geleerter Abwassergrube
A78: 3.2. | B78: Abwasserkanal | D78: erstellt | F78: Alter: | H78: Jahre
B79: Kosten | D79: höchstens | E79: =IF(G78>0,MIN(2200,C79),0) | F79: abzüglich | H79: =G78/100*3 | I79: (3%/Jahr) | J79: = | K79: =IF(C79>74,ROUND(E79-E79*H79,2),0) | N79: Summe K56:K74
N80: =SUM(K61:K77)
A81: Baulichkeiten insgesamt: | K81: =K61+K71+K75+K77+K79
A82: 4. | B82: Baubeschreibung
A101: 5. | B101: Bewertete bebaute Fläche | F101: =A17+A26+A35+A52 | H101: m²
A102: =IF(E76=("fehlt"),("Genehmigte Abwassersammelgrube ohne Bewertung, da ein zeitnahes Dichtigkeitsgutachten fehlt, siehe auch Anlage IV, Blatt 3."),("."))
A103: 6. | B103: Abzüge wegen nicht beräumter Baulichkeiten | F103: m³ | G103: Preis | H103: Summe
H104: =SUM(F104*G104) | M104: Abwassersammeltanks und monolithische Betongruben mit gültigem Dichtheitsnachweis sind nach Ablauf von 16 Jahren nicht weiter abzuschreiben.
A105: 7. | B105: Nicht geleerte Abwassersammelgrube
A108: Berlin, den | C108: =Formalien!$E$15 | E108: Wertermittler: | F108: =Formalien!$E$12
K109: Seite 3

Sheet Mängelliste
A1: ="Kleingartenanlage: "&Formalien!$E$3 -> Kleingartenanlage: | D1: Parzelle: | E1: =Formalien!$E$4
A2: Laube | E2: =Formalien!$E$5
A3: Mängeltabelle für Ermittlung der Normalherstellungskosten | E3: Abzug maximal | F3: Abzug konkret
A4: Bauteil | B4: Mangel
A5: Dach | C5: Sparren - Abstand nicht fachgerecht, größer als 60-80 cm | E5: 0.2
C6: Sparren - Risse durch Belastung | D6: Dach nicht horizentral
C7: Regenrinne oder Fallrohr nicht fachgerecht | D7: Dachoberfläche beschädigt
C8: Fallrohr ohne Ableitung von der Laube | D8: keine Traufkante
C9: Dachoberfläche nicht fachgerecht | D9: Dachfenster/Dachluke fehlerhaft
C10: Ortgang fehlerhaft oder fehlt | D10: Feuchtigkeit in der Dachkonstruktion
C11: muffiger Geruch unter dem Dach | D11: unzulässige Höhe der Laube
C12: Feuchtigkeit in der Dachkonstruktion
A13: Decken | C13: Decke hängt durch | D13: Feuchtigkeitsflecken | E13: 0.1
C14: loser Putz/Hohlstellen | D14: Verkleidung defekt
C15: Anstrich
A16: Wände | C16: Rohbaumauerwerk | D16: Hohlstellen im Putz | E16: 0.13
C17: Risse | D17: defekte Verkleidung
C18: Feuchtigkeitsflecken | D18: Horizontalsperre defekt
C19: Wände nicht lotgerecht | D19: keine fachgerechte Ausführung
C20: offene Fugen
A21: Fußboden | C21: Hohlstellen im Estrich | D21: Risse | E21: 0.1
C22: Dielung gibt nach | D22: Fußboden nicht waagerecht
C23: Feuchtigkeitsflecken
A24: Fundament | C24: Fundamenttiefe nicht erkennbar | D24: Setzungen | E24: 0.2
C25: Kein Spritzwassersockel (mindestens 25 cm) | D25: Brüche
C26: Spritzwassersockel fehlerhaft | D26: nicht maßgrecht
C27: keine fachgerechte Ausführung (Festigkeit)
A28: Ausbau außen | C28: Anstrich fehlerhaft | D28: Verkleidung fehlerhaft | E28: 0.05
C29: Regenrinne fehlerhaft | D29: Fallrohr fehlerhaft
A30: Ausbau innen | C30: Rückflussverhinderer fehlt | E30: 0.07
C31: Anstrich, Tapeten, Verkleidung fehlerhaft | D31: Fußbodenbelag fehlerhaft
C32: Treppen, Leitern fehlerhaft
C33: Wasseranschluß fehlerhaft bei vorhandener Abwassersammelanlage
A34: Bauelemente | C34: Fenster - Gladichtung fehlerhaft (Kitt) | D34: Fenster - Anstrich defekt | E34: 0.05
C35: Fenster klemmt | D35: Fenster undicht
C36: Fensterläden nich ordnungsgemäß | D36: Fensterläden - Anstrich defekt
C37: Tür für Außenbereich ungeeignet | D37: Tür klemmt
C38: Tür unddicht | D38: Tür - Anstrich defekt
C39: Einbruchsschäden
A40: Schädlinge | C40: Schimmel | D40: Marder, Ratten usw. | E40: 0.1
C41: Hausschwamm | D41: Taubenkot
A42: Sonderabfall | C42: Asbest | D42: Dachpappe | E42: 0.1
A43: Laube nicht beräumt | E43: 0.1
A44: Baulichkeiten nicht fertiggestellt: Sie werden zunächst nach dem Stand des Ausbaus bewertet. Es können Abschläge für Mängel kalkuliert werden (z.B. Witterungseinflüsse), die konkret zu benennen sind. | E44: Je nach Zustand
A45: Nicht ausgewiesene Mängel sind dem Bauteil der Anlage zuzuordnen.
E46: Gesamtabzug % | F46: =SUM(F2:F45)
F48: Seite 4

Sheet Außenanlagen
A1: Anlage 2 – Bewertung Außenanlagen
A2: Kleingartenanlage: | D2: =Formalien!$E$3 | K2: Parzelle: | L2: =Formalien!$E$4
A3: Parzellenfläche lt. Vertrag: | E3: =Formalien!$E$16 | F3: davon 6 % zulässige versiegelte Fläche: | J3: =(E3-24)/100*6 | K3: m²
A4: Name des Unterpächters: | E4: =Formalien!$E$6
A7: Beschreibung Außenanlagen
A13: An- zahl | B13: Maß- einheit | C13: Auflistung Außenanlagen - Art | K13: Entschädigungswert
K14: Einzelpreis | L14: Gesamtpreis
L15: =ROUND(A15*K15,2)
L16: =ROUND(A16*K16,2)
L17: =ROUND(A17*K17,2)
L18: =ROUND(A18*K18,2)
L19: =ROUND(A19*K19,2)
L20: =ROUND(A20*K20,2)
L21: =ROUND(A21*K21,2)
L22: =ROUND(A22*K22,2)
L23: =ROUND(A23*K23,2)
L24: =ROUND(A24*K24,2)
L25: =ROUND(A25*K25,2)
L26: =ROUND(A26*K26,2)
... L45: =ROUND(A45*K45,2)
I46: Außenanlagen insgesamt: | L46: =SUM(L15:L45)
A48: Berlin, den | C48: =Formalien!$E$15 | G48: Wertermittler: | H48: =Formalien!$E$13 | L48: Seite 5

Sheet Aufwuchs I
A1: Anlage 3 – Bewertung Aufwuchs
A2: Kleingartenanlage: | D2: =Formalien!$E$3 | K2: Parzelle: | L2: =Formalien!$E$4
A3: Parzellenfläche lt. Vertrag: | E3: =Formalien!$E$16
A4: Name des Unterpächters: | E4: =Formalien!$E$6
A7: Beschreibung Aufwuchs:
A16: An- zahl | B16: Maß-einheit | C16: Auflistung Aufwuchs - Art | K16: Entschädigungswert
K17: Einzelpreis | L17: Gesamtpreis
L18: =ROUND(A18*K18,2)
L19: =ROUND(A19*K19,2)
L20: =ROUND(A20*K20,2)
L21: =ROUND(A21*K21,2)
L22: =ROUND(A22*K22,2)
L23: =ROUND(A23*K23,2)
L24: =ROUND(A24*K24,2)
L25: =ROUND(A25*K25,2)
L26: =ROUND(A26*K26,2)
L27: =ROUND(A27*K27,2)
L28: =ROUND(A28*K28,2)
L29: =ROUND(A29*K29,2)
... L45: =ROUND(A45*K45,2)
H46: Aufwuchs insgesamt/Übertrag: | L46: =SUM(L18:L45)
A48: Berlin, den | C48: =Formalien!$E$15 | F48: Wertermittler: | H48: =Formalien!$E$13 | L48: Seite 6

Sheet Aufwuchs II
A1: Anlage 3a – Bewertung Aufwuchs
A2: Kleingartenanlage: | D2: =Formalien!$E$3 | K2: Parzelle: | L2: =Formalien!$E$4
A3: Parzellenfläche lt. Vertrag: | E3: =Formalien!$E$16
A4: Name des Unterpächters: | E4: =Formalien!$E$6
A7: An- zahl | B7: Maß-einheit | C7: Auflistung Aufwuchs - Art | K7: Entschädigungswert
K8: Einzelpreis | L8: Gesamtpreis
A9: Übertrag von Anlage 3: | L9: ='Aufwuchs I'!$L$46
L10: =ROUND(A10*K10,2)
L11: =ROUND(A11*K11,2)
L12: =ROUND(A12*K12,2)
L13: =ROUND(A13*K13,2)
L14: =ROUND(A14*K14,2)
L15: =ROUND(A15*K15,2)
L16: =ROUND(A16*K16,2)
L17: =ROUND(A17*K17,2)
L18: =ROUND(A18*K18,2)
L19: =ROUND(A19*K19,2)
L20: =ROUND(A20*K20,2)
L21: =ROUND(A21*K21,2)
... L45: =ROUND(A45*K45,2)
I46: Aufwuchs insgesamt: | L46: =SUM(L9:L45)
A48: Berlin, den | C48: =Formalien!$E$15 | E48: Wertermittler: | G48: =Formalien!$E$13 | L48: Seite 6a

Sheet AnlIV (Blatt 3)ASG
A1: Anlage IV (Blatt3)
A2: Kleingartenanlage: | D2: =Formalien!$E$3 -> 0 | F2: Parz.Nr.: | G2: =Formalien!$E$4 -> 0
A3: Parzellenfläche lt. Vertrag: | D3: =Formalien!$E$16 -> 0 | E3: m²
A4: Name des Unterpächters: | D4: =Formalien!$E$6 -> 0
A6: zu 3. der Anlage I und zu 9. der Anlage IV zur Wertermittlung vom | G6: =Formalien!$E$14 -> 0
A8: Die Abwassersammelgrube ist nicht entschädigungsfähig, da ein Dichtig-
A9: keitszertifikat fehlt.
A10: Die Abwassersammelgrube ist mit | D10: =F50 -> 0 | E10: *) zu entschädigen, wenn der schei-
A11: dende Unterpächter ein Zertifikat vorweisen kann.
A18: Achtung!! Wird die Begutachtung nachgeholt, muß nachgewiesen werden, dass die Abwassersammelgrube nach der Begutachtung geleert worden ist, sonst fällt eine Abzug von 150,00 € für die nicht geleerte Grube an.
A26: Die ordnungsgemäße Durchführung der Dichtigkeitsprüfungen hat nach den DIN 1986-30 und EN 1610 sowie EN 12566-1 zu erfolgen und ist im Dichtigkeitsgutachten zu dokumentieren. Aus den Prüfprotokollen muss die Art der Prüfung und die zutreffenden Parameter, wie z.B. - bei der Prüfung mit Wasser - Material, Durchmesser der Rohrleitungen, Haltungslängen, benetzte Flächen, Volumen und Füllmengen, zulässige Wasserzugabe, gemessene Wasserzugabe und Prüfdauer, ersichtlich sein. Die Dichtheitsprüfungen sind auf Kosten des Betreibers von einem zertifizierten Sachverständigen durchführen zu lassen. Dieser kennt die zutreffenden relevanten Parameter und gewährleistet mit der Erstellung einer adäquaten Dokumentation (Prüfprotokoll) deren Anerkennung durch die Behörde.
A48: *) Alter | C48: Jahre | D48: Grundwert | F48: pro m³
A49: ./. | B49: =ROUND(B48*3,0) -> 0 | C49: Altersabzug = | E49: =ROUND(E48-E48*B49%,2) -> 0 | F49: pro m³
B50: =E49 -> 0 | C50: X | E50: m³ = | F50: =ROUND(B50*D50,2) -> 0

Sheet Anl IV Schuppen
A1: Anlage IV (Blatt 1 ) Kleingartenanlage: | E1: =Formalien!$E$3 -> 0 | J1: =Formalien!$E$5 -> 0
A2: Unterpächter: | D2: =Formalien!$E$6 -> 0 | H2: Parz.Nr. | J2: =Formalien!$E$4 -> 0
A3: Lt. UP-Vertrag Baulichkeiten von | G3: =#REF! -> #REF! | H3: m² übernommen
A5: Abrißanordnungen und Auflagen für den neuen Unterpächter und etwaiger
A6: Einbehalt für Entfernung von nicht gestatteten baulichen Anlagen, Abfällen
A7: und nicht zulässigen bzw. nutzbaren Bepflanzungen.
A9: 1.
A17: 1.1. Bauteil | C17: =#REF! -> #REF! | D17: =#REF! -> #REF! | E17: =#REF! -> #REF! | F17: =#REF! -> #REF! | J17: =#REF! -> #REF!
A18: zu | C18: =#REF! -> #REF! | D18: =#REF! -> #REF! | F18: =#REF! -> #REF! | H18: =#REF! -> #REF! | I18: =#REF! -> #REF!
A19: 1.2. Bauteil | C19: =#REF! -> #REF! | D19: =#REF! -> #REF! | E19: =#REF! -> #REF! | F19: =#REF! -> #REF! | J19: =#REF! -> #REF!
A20: zu | C20: =#REF! -> #REF! | D20: =#REF! -> #REF! | F20: =#REF! -> #REF! | H20: =#REF! -> #REF! | I20: =#REF! -> #REF!
A21: 1.3. Bauteil | C21: =#REF! -> #REF! | D21: =#REF! -> #REF! | E21: =#REF! -> #REF! | F21: =#REF! -> #REF! | J21: =#REF! -> #REF!
A22: zu | C22: =#REF! -> #REF! | D22: =#REF! -> #REF! | F22: =#REF! -> #REF! | H22: =#REF! -> #REF! | I22: =#REF! -> #REF!
A23: 1.4. Bauteil | C23: =#REF! -> #REF! | D23: =#REF! -> #REF! | E23: =#REF! -> #REF! | F23: =#REF! -> #REF! | G23: =#REF! -> #REF! | J23: =#REF! -> #REF!
A24: zu | C24: =#REF! -> #REF! | D24: =#REF! -> #REF! | E24: =#REF! -> #REF! | F24: =#REF! -> #REF! | H24: =#REF! -> #REF! | I24: =#REF! -> #REF!
A25: *) Dach, gesamtes Gerüst, Seitenwände und Balustraden. Der Terrassenboden nur, wenn ausdrücklich angeordnet.
B26: =#REF! -> #REF! | D26: =#REF! -> #REF!
A27: 1.5. | B27: =#REF! -> #REF!
A44: 2. | B44: Zu entfernender Aufwuchs einschl. Baumstumpf bzw. Wurzelballen gemäß Anlage III
A45: 2.1. | B45: =#REF! -> #REF! | C45: =#REF! -> #REF! | F45: =#REF! -> #REF! | G45: =#REF! -> #REF! | H45: =#REF! -> #REF! | I45: =#REF! -> #REF!
A46: 2.2. | B46: =#REF! -> #REF! | C46: =#REF! -> #REF! | F46: =#REF! -> #REF! | G46: =#REF! -> #REF! | H46: =#REF! -> #REF! | I46: =#REF! -> #REF!
A47: 2.3. | B47: =#REF! -> #REF! | C47: =#REF! -> #REF! | F47: =#REF! -> #REF! | G47: =#REF! -> #REF! | H47: =#REF! -> #REF! | I47: =#REF! -> #REF!
A48: 2.4. | B48: =#REF! -> #REF! | C48: =#REF! -> #REF! | F48: =#REF! -> #REF! | G48: =#REF! -> #REF! | H48: =#REF! -> #REF! | I48: =#REF! -> #REF!
A49: 2.5. | B49: =#REF! -> #REF! | E49: =#REF! -> #REF! | J49: =#REF! -> #REF!
A50: 2.6. | B50: =#REF! -> #REF! | C50: =#REF! -> #REF! | H50: =#REF! -> #REF! | I50: =#REF! -> #REF!
A51: 2.7. | B51: =#REF! -> #REF! | C51: =#REF! -> #REF! | H51: =#REF! -> #REF! | I51: =#REF! -> #REF!
A52: 2.8. | B52: =#REF! -> #REF! | C52: =#REF! -> #REF! | K52: =#REF! -> #REF!
B53: =#REF! -> #REF! | D53: =#REF! -> #REF!
B54: =#REF! -> #REF!
B56: In der Zeit vom 1.März bis zum 30.September sollten aus Gründen des Naturschutzes insbesondere des Vogelschutzes keine Bäume sowie keine größeren Gehölze entfernt und/oder beschnitten werden. Bei Fäll- und Schnittmaßnahmen ist besonders darauf zu achten, dass brütende Vögel nicht gestört werden. Auf das Bundesnaturschutzgesetz und auf die Baumschutzverordnung Berlin in ihren jeweils geltenden Fassungen wird hingewiesen. Hecken auf und an der Parzelle sind grundsätzlich ganzjährig auf eine Höhe von 1,25m zu halten.
F61: Summe Blatt 1: | I61: =SUM(I45:J51)+I18+I20+I22+I24 -> #REF!
A65: Anlage IV (Blatt 2) | H65: =Formalien!$F$5 -> 0
B66: Kleingartenanlage: | D66: =$E$1 -> 0 | G66: Parz.Nr.: | H66: =J2 -> 0
E68: Übertrag Anlage IV (Blatt 1) : | I68: =I61 -> #REF!
A69: 3. | B69: Zu entfernende Aussenanlagen gemäß Anlage II
A70: 3.1. | B70: =#REF! -> #REF! | C70: =#REF! -> #REF!
D71: =#REF! -> #REF! | E71: =#REF! -> #REF! | F71: =#REF! -> #REF! | H71: =#REF! -> #REF! | I71: =#REF! -> #REF!
A72: 3.2. | B72: =#REF! -> #REF! | C72: =#REF! -> #REF! | E72: =#REF! -> #REF! | H72: =#REF! -> #REF! | I72: =#REF! -> #REF!
A73: 3.3. | B73: =#REF! -> #REF! | C73: =#REF! -> #REF! | E73: =#REF! -> #REF! | F73: =#REF! -> #REF! | H73: =#REF! -> #REF! | I73: =#REF! -> #REF!
A74: 3.4. | B74: =#REF! -> #REF! | H74: =#REF! -> #REF! | I74: =#REF! -> #REF!
A75: 3.5. | B75: =#REF! -> #REF! | H75: =#REF! -> #REF! | I75: =#REF! -> #REF!
A76: 3.6. | B76: =#REF! -> #REF! | H76: =#REF! -> #REF! | I76: =#REF! -> #REF!
A77: 3.7. | B77: =#REF! -> #REF! | H77: =#REF! -> #REF! | I77: =#REF! -> #REF!
A78: 3.8. | B78: =#REF! -> #REF! | I78: =#REF! -> #REF!
A80: 3.9. | B80: =#REF! -> #REF! | D80: =#REF! -> #REF!
A81: 3.10. | B81: =#REF! -> #REF!
A84: 4. | B84: Die neuen Unterpächter sind verpflichtet, von einem etwa vorhandenen zweiflügeligen Tor die eine
B85: Torhälfte zu befestigen bzw. einflüglig zu setzen und ggf. den Zaun zu begradigen.
B86: Ist eine zweite Gartenpforte vorhanden, ist das Tor vollständig dauerhaft zu verschließen.
B87: Das Abstellen von Kraftfahrzeugen auf der Parzelle ist nicht zulässig. (Ziffer 21 der Gartenordnung) | K87: =#REF! -> #REF!
A88: 5. | B88: Etwa vorhandene Schornsteine sind still zu legen, etwa vorhandene offene Feuerstellen
B89: (Herde, Öfen, Kamine, Öl- oder Gasheizungsanlagen) sind zu entfernen. | K89: =#REF! -> #REF!
A90: 6. | B90: Die Auflagen zu 1. bis 5. sind vom neuen Unterpächter binnen 9 Monate nach Übernahme der Parzelle zu erfüllen
A91: =#REF! -> #REF! | B91: =#REF! -> #REF! | J91: =#REF! -> #REF!
A92: Abfuhrbescheinigiung vom | G92: =#REF! -> #REF! | H92: lag nicht vor | K92: =#REF! -> #REF!
B93: =#REF! -> #REF! | E93: =#REF! -> #REF! | F93: =#REF! -> #REF! | G93: =#REF! -> #REF! | H93: =#REF! -> #REF! | J93: =#REF! -> #REF! | K93: =#REF! -> #REF!
A94: 8.a | B94: =#REF! -> #REF!
B95: =#REF! -> #REF!
B96: =#REF! -> #REF! | E96: =#REF! -> #REF! | F96: =#REF! -> #REF! | G96: =#REF! -> #REF! | H96: =#REF! -> #REF! | I96: =#REF! -> #REF! | K96: =#REF! -> #REF!
A97: 8.b | B97: =#REF! -> #REF! | K97: =#REF! -> #REF!
B98: =#REF! -> #REF!
B99: =#REF! -> #REF! | H99: =#REF! -> #REF! | J99: =#REF! -> #REF!
A100: 8.c | B100: =#REF! -> #REF! | H100: =#REF! -> #REF! | J100: =#REF! -> #REF!
B101: =#REF! -> #REF! | H101: =#REF! -> #REF! | I101: =#REF! -> #REF! | K101: =#REF! -> #REF!
A102: 9. | B102: entfällt
K106: =#REF! -> #REF!
A108: 9.a | B108: entfällt | E108: =#REF! -> #REF!
H110: =#REF! -> #REF! | K110: =#REF! -> #REF!
A111: 10. | B111: Die neuen Unterpächter tragen die Verkehrssicherungspflicht und die Kosten des Unterhalts
B112: und einer etwaigen Entfernung eines unter Baumschutz stehenden Aufwuchses. | K112: =#REF! -> #REF!
B113: Auf die Vorschriften der Berliner Baumschutzverordnung wird hingewiesen.
A114: 11. | B114: =#REF! -> #REF! | D114: =#REF! -> #REF!
B115: =#REF! -> #REF!
B116: =#REF! -> #REF!
A121: Datum: | C121: =Formalien!$E$14 -> 0 | E121: Wertermittler | F121: =Formalien!$E$12 -> 0 | H121: / | I121: =Formalien!$E$13 -> 0
A123: Datum: | G123: Bezirksverband Vorstand:

Sheet Anl IV Dach
A1: Anlage IV (Blatt 1 ) Kleingartenanlage: | E1: =Formalien!$E$3 -> 0 | J1: =Formalien!$E$5 -> 0
A2: Unterpächter: | D2: =Formalien!$E$6 -> 0 | H2: Parz.Nr. | J2: =Formalien!$E$4 -> 0
A3: Lt. UP-Vertrag Baulichkeiten von | G3: =#REF! -> #REF! | H3: m² übernommen
A5: Abrißanordnungen und Auflagen für den neuen Unterpächter und etwaiger
A6: Einbehalt für Entfernung von nicht gestatteten baulichen Anlagen, Abfällen
A7: und nicht zulässigen bzw. nutzbaren Bepflanzungen.
A9: 1.
A17: 1.1. Bauteil | C17: =#REF! -> #REF! | D17: =#REF! -> #REF! | E17: =#REF! -> #REF! | F17: =#REF! -> #REF! | J17: =#REF! -> #REF!
A18: zu | C18: =#REF! -> #REF! | D18: =#REF! -> #REF! | F18: =#REF! -> #REF! | H18: =#REF! -> #REF! | I18: =#REF! -> #REF!
A19: 1.2. Bauteil | C19: =#REF! -> #REF! | D19: =#REF! -> #REF! | E19: =#REF! -> #REF! | F19: =#REF! -> #REF! | J19: =#REF! -> #REF!
A20: zu | C20: =#REF! -> #REF! | D20: =#REF! -> #REF! | F20: =#REF! -> #REF! | H20: =#REF! -> #REF! | I20: =#REF! -> #REF!
A21: 1.3. Bauteil | C21: =#REF! -> #REF! | D21: =#REF! -> #REF! | E21: =#REF! -> #REF! | F21: =#REF! -> #REF! | J21: =#REF! -> #REF!
A22: zu | C22: =#REF! -> #REF! | D22: =#REF! -> #REF! | F22: =#REF! -> #REF! | H22: =#REF! -> #REF! | I22: =#REF! -> #REF!
A23: 1.4. Bauteil | C23: =#REF! -> #REF! | D23: =#REF! -> #REF! | E23: =#REF! -> #REF! | F23: =#REF! -> #REF! | G23: =#REF! -> #REF! | J23: =#REF! -> #REF!
A24: zu | C24: =#REF! -> #REF! | D24: =#REF! -> #REF! | E24: =#REF! -> #REF! | F24: =#REF! -> #REF! | H24: =#REF! -> #REF! | I24: =#REF! -> #REF!
A25: *) Dach, gesamtes Gerüst, Seitenwände und Balustraden. Der Terrassenboden nur, wenn ausdrücklich angeordnet.
B26: =#REF! -> #REF! | D26: =#REF! -> #REF!
A27: 1.5. | B27: =#REF! -> #REF!
A41: 2. | B41: Zu entfernender Aufwuchs einschl. Baumstumpf bzw. Wurzelballen gemäß Anlage III
A42: 2.1. | B42: =#REF! -> #REF! | C42: =#REF! -> #REF! | F42: =#REF! -> #REF! | G42: =#REF! -> #REF! | H42: =#REF! -> #REF! | I42: =#REF! -> #REF!
A43: 2.2. | B43: =#REF! -> #REF! | C43: =#REF! -> #REF! | F43: =#REF! -> #REF! | G43: =#REF! -> #REF! | H43: =#REF! -> #REF! | I43: =#REF! -> #REF!
A44: 2.3. | B44: =#REF! -> #REF! | C44: =#REF! -> #REF! | F44: =#REF! -> #REF! | G44: =#REF! -> #REF! | H44: =#REF! -> #REF! | I44: =#REF! -> #REF!
A45: 2.4. | B45: =#REF! -> #REF! | C45: =#REF! -> #REF! | F45: =#REF! -> #REF! | G45: =#REF! -> #REF! | H45: =#REF! -> #REF! | I45: =#REF! -> #REF!
A46: 2.5. | B46: =#REF! -> #REF! | E46: =#REF! -> #REF! | J46: =#REF! -> #REF!
A47: 2.6. | B47: =#REF! -> #REF! | C47: =#REF! -> #REF! | H47: =#REF! -> #REF! | I47: =#REF! -> #REF!
A48: 2.7. | B48: =#REF! -> #REF! | C48: =#REF! -> #REF! | H48: =#REF! -> #REF! | I48: =#REF! -> #REF!
A49: 2.8. | B49: =#REF! -> #REF! | C49: =#REF! -> #REF! | K49: =#REF! -> #REF!
B50: =#REF! -> #REF! | D50: =#REF! -> #REF!
B51: =#REF! -> #REF!
B53: In der Zeit vom 1.März bis zum 30.September sollten aus Gründen des Naturschutzes insbesondere des Vogelschutzes keine Bäume sowie keine größeren Gehölze entfernt und/oder beschnitten werden. Bei Fäll- und Schnittmaßnahmen ist besonders darauf zu achten, dass brütende Vögel nicht gestört werden. Auf das Bundesnaturschutzgesetz und auf die Baumschutzverordnung Berlin in ihren jeweils geltenden Fassungen wird hingewiesen. Hecken auf und an der Parzelle sind grundsätzlich ganzjährig auf eine Höhe von 1,25m zu halten.
F58: Summe Blatt 1 A: | I58: =SUM(I42:J48)+I18+I20+I22+I24 -> #REF!
A62: Anlage IV (Blatt 2) | H62: =Formalien!$F$5 -> 0
B63: Kleingartenanlage: | D63: =$E$1 -> 0 | G63: Parz.Nr.: | H63: =J2 -> 0
E65: Übertrag Anlage IV (Blatt 1 A) 1. - 3. : | I65: =I58 -> #REF!
A66: 3. | B66: Zu entfernende Aussenanlagen gemäß Anlage II
A67: 3.1. | B67: =#REF! -> #REF! | C67: =#REF! -> #REF!
D68: =#REF! -> #REF! | E68: =#REF! -> #REF! | F68: =#REF! -> #REF! | H68: =#REF! -> #REF! | I68: =#REF! -> #REF!
A69: 3.2. | B69: =#REF! -> #REF! | C69: =#REF! -> #REF! | E69: =#REF! -> #REF! | H69: =#REF! -> #REF! | I69: =#REF! -> #REF!
A70: 3.3. | B70: =#REF! -> #REF! | C70: =#REF! -> #REF! | E70: =#REF! -> #REF! | F70: =#REF! -> #REF! | H70: =#REF! -> #REF! | I70: =#REF! -> #REF!
A71: 3.4. | B71: =#REF! -> #REF! | H71: =#REF! -> #REF! | I71: =#REF! -> #REF!
A72: 3.5. | B72: =#REF! -> #REF! | H72: =#REF! -> #REF! | I72: =#REF! -> #REF!
A73: 3.6. | B73: =#REF! -> #REF! | H73: =#REF! -> #REF! | I73: =#REF! -> #REF!
A74: 3.7. | B74: =#REF! -> #REF! | H74: =#REF! -> #REF! | I74: =#REF! -> #REF!
A75: 3.8. | B75: =#REF! -> #REF! | I75: =#REF! -> #REF!
A77: 3.9. | B77: =#REF! -> #REF! | D77: =#REF! -> #REF!
A78: 3.10. | B78: =#REF! -> #REF!
A81: 4. | B81: Die neuen Unterpächter sind verpflichtet, von einem etwa vorhandenen zweiflügeligen Tor die eine
B82: Torhälfte zu befestigen bzw. einflüglig zu setzen und ggf. den Zaun zu begradigen.
B83: Ist eine zweite Gartenpforte vorhanden, ist das Tor vollständig dauerhaft zu verschließen.
B84: Das Abstellen von Kraftfahrzeugen auf der Parzelle ist nicht zulässig. (Ziffer 21 der Gartenordnung) | K84: =#REF! -> #REF!
A85: 5. | B85: Etwa vorhandene Schornsteine sind still zu legen, etwa vorhandene offene Feuerstellen
B86: (Herde, Öfen, Kamine, Öl- oder Gasheizungsanlagen) sind zu entfernen. | K86: =#REF! -> #REF!
A87: 6. | B87: Die Auflagen zu 1. bis 5. sind vom neuen Unterpächter binnen 9 Monate nach Übernahme der Parzelle zu erfüllen
A88: =#REF! -> #REF! | B88: =#REF! -> #REF! | J88: =#REF! -> #REF!
A89: Abfuhrbescheinigiung vom | G89: =#REF! -> #REF! | H89: lag nicht vor | K89: =#REF! -> #REF!
B90: =#REF! -> #REF! | E90: =#REF! -> #REF! | F90: =#REF! -> #REF! | G90: =#REF! -> #REF! | H90: =#REF! -> #REF! | J90: =#REF! -> #REF! | K90: =#REF! -> #REF!
A91: 8.a | B91: =#REF! -> #REF!
B92: =#REF! -> #REF!
B93: =#REF! -> #REF! | E93: =#REF! -> #REF! | F93: =#REF! -> #REF! | G93: =#REF! -> #REF! | H93: =#REF! -> #REF! | I93: =#REF! -> #REF! | K93: =#REF! -> #REF!
A94: 8.b | B94: =#REF! -> #REF! | K94: =#REF! -> #REF!
B95: =#REF! -> #REF! | K95: =#REF! -> #REF!
B96: =#REF! -> #REF! | H96: =#REF! -> #REF! | J96: =#REF! -> #REF!
A97: 8.c | B97: =#REF! -> #REF! | H97: =#REF! -> #REF! | J97: =#REF! -> #REF!
B98: =#REF! -> #REF! | H98: =#REF! -> #REF! | I98: =#REF! -> #REF!
A99: 9. | B99: entfällt
K103: =#REF! -> #REF!
A105: 9.a | B105: entfällt | E105: =#REF! -> #REF!
H107: =#REF! -> #REF! | K107: =#REF! -> #REF!
A108: 10. | B108: Die neuen Unterpächter tragen die Verkehrssicherungspflicht und die Kosten des Unterhalts
B109: und einer etwaigen Entfernung eines unter Baumschutz stehenden Aufwuchses. | K109: =#REF! -> #REF!
B110: Auf die Vorschriften der Berliner Baumschutzverordnung wird hingewiesen.
A111: 11. | B111: entfällt | D111: =#REF! -> #REF!
B112: =#REF! -> #REF!
A113: Datum: | C113: =Formalien!$E$14 -> 0 | E113: Wertermittler | F113: =Formalien!$E$12 -> 0 | H113: / | I113: =Formalien!$E$13 -> 0
A115: Datum: | G115: Bezirksverband d.Vorstand:

Sheet Deckbl UPV neu (Sicherheit)
A1: Bezirksverband der Gartenfreunde Pankow e.V.
A2: Quickborner Str. 12, 13158 Berlin, info@gartenfreunde-pankow.de
A3: Wertermittlung bei Unterpächterwechsel
A6: Name des Unterpächters: | C6: =Formalien!$E$6
A7: Kleingartenanlage: | C7: =Formalien!$E$3
C8: =Formalien!$E$5 | F8: Parzellen Nr.: | G8: =Formalien!$E$4
A9: Wertermittlung am: | C9: =Formalien!$E$14
A10: Anwesend waren: | B10: Wertermittler: | D10: =Formalien!$E$12
A11: Wertermittler: | D11: =Formalien!$E$13
A12: Für den Unterpächter: | D12: =Formalien!$E$10
A13: Für den Kolonieverein: | D13: =Formalien!$E$9
A14: Ergebnisse der Wertermittlung:
A16: ='Deckbl UPV '!A21 | D16: =Baulichkeiten!$K$81 | E16: ='Deckbl UPV '!F21
A17: ='Deckbl UPV '!A22 | D17: ='Deckbl UPV '!E22
A18: ='Deckbl UPV '!#REF! | D18: ='Deckbl UPV '!E23
A19: ='Deckbl UPV '!K24 | D19: ='Deckbl UPV '!E24
A20: ='Deckbl UPV '!K26
A21: ='Deckbl UPV '!C27 | D21: ='Deckbl UPV '!E27
A22: ='Deckbl UPV '!C28 | D22: ='Deckbl UPV '!E26
A24: ='Deckbl UPV '!#REF! | D24: ='Deckbl UPV '!E28
A56: Datum: | B56: xx.xx.xxxx | D56: Unterschrift BV

Sheet Deckbl UPV  (alt)
A1: Bezirksverband der Gartenfreunde Pankow e.V.
A2: Quickborner Str. 12, 13158 Berlin, info@gartenfreunde-pankow.de
A3: Wertermittlung bei Unterpächterwechsel
A6: Name des Unterpächters: | C6: =Formalien!$E$6
A7: Kleingartenanlage: | C7: =Formalien!$E$3
C8: =Formalien!$E$5 | F8: Parzellen Nr.: | G8: =Formalien!$E$4
A9: Wertermittlung am: | C9: =Formalien!$E$14
A10: Anwesend waren: | B10: Wertermittler: | D10: =Formalien!$E$12
A11: Wertermittler: | D11: =Formalien!$E$13
A12: Für den Unterpächter: | D12: =Formalien!$E$10
A13: Für den Kolonieverein: | D13: =Formalien!$E$9
A14: Ergebnisse der Wertermittlung:
A16: ='Deckbl UPV '!A21 | D16: ='Deckbl UPV '!E21 | E16: ='Deckbl UPV '!F21
A17: ='Deckbl UPV '!A22 | D17: ='Deckbl UPV '!E22
A18: Aufwuchs lt. Anlage II: | D18: ='Deckbl UPV '!E23
C19: ='Deckbl UPV '!K24 | D19: ='Deckbl UPV '!E24
C20: ='Deckbl UPV '!K26
C21: ='Deckbl UPV '!C27
C22: ='Deckbl UPV '!C28 | D22: ='Deckbl UPV '!E26
C24: ='Deckbl UPV '!#REF! | D24: ='Deckbl UPV '!E28
A56: Datum: | B56: xx.xx.xxxx | D56: Unterschrift BV

Sheet Deckbl Auftragsgutachten
A1: Bezirksverband der Gartenfreunde Pankow e.V.
A2: Quickborner Str. 12, 13158 Berlin, info@gartenfreunde-pankow.de
A3: Wertermittlung im Auftrag
B6: Auftraggeber: | C6: =Formalien!$E$7
A7: vertreten durch Rechtsanwalt: | C7: =Formalien!$E$8
A8: Name des Unterpächters: | C8: =Formalien!$E$6
A9: Kleingartenanlage: | C9: =Formalien!$E$3
C10: =Formalien!$E$5 | F10: Parzellen Nr.: | G10: =Formalien!$E$4
A11: Wertermittlung am: | C11: =Formalien!$E$14
A12: Anwesend waren: | B12: Wertermittler: | D12: =Formalien!$E$12
A13: Wertermittler: | D13: =Formalien!$E$13
A14: Für den Unterpächter: | D14: =Formalien!$E$10
C15: Für den Auftraggeber: | D15: =Formalien!$E$11
A16: Für den Kolonieverein: | D16: =Formalien!$E$9
A17: Ergebnisse der Wertermittlung:
A19: ='Deckbl UPV '!A21 | D19: ='Deckbl UPV '!E21 | E19: (einschließlich Abwasseranlage)
A20: ='Deckbl UPV '!A22 | D20: ='Deckbl UPV '!E22
A21: ='Deckbl UPV '!#REF! | D21: ='Deckbl UPV '!E23
A22: ='Deckbl UPV '!K24 | D22: ='Deckbl UPV '!E24
A23: ='Deckbl UPV '!K26
A24: ='Deckbl UPV '!C27
A25: ='Deckbl UPV '!C28 | D25: ='Deckbl UPV '!E26
C26: ='Deckbl UPV '!#REF! | D26: ='Deckbl UPV '!E28
A54: Datum: | B54: xx.xx.xxxx | D54: Unterschrift BV

Sheet Beseitigungsauflagen
C1: Beseitigungskosten | G1: Reg.Nr.:
B3: Name des Unterpächters | D3: Kleingartenanlage | G3: Kleingarten-Nr.
B6: 0 | D6: 0 | G6: 0
E9: Menge | G9: Einheit | H9: Gesamt
E10: X | G10: € | H10: €
B11: 1. Bauliche Anlagen und Fundamente
H12: =SUM(E12*G12) -> 0
H13: =SUM(E13*G13) -> 0
H14: =SUM(E14*G14) -> 0
H15: =SUM(E15*G15) -> 0
H16: =SUM(E16*G16) -> 0
D17: Summe der Beseitigungskosten: | H17: =SUM(H12:H16) -> 0
B19: 2. Aufwuchs
H20: =SUM(E20*G20) -> 0
H21: =SUM(E21*G21) -> 0
H22: =SUM(E22*G33) -> 0
H23: =SUM(E23*G23) -> 0
H24: =SUM(E24*G24) -> 0
H25: =SUM(E25*G25) -> 0
H26: =SUM(E26*G26) -> 0
H27: =SUM(E27*G27) -> 0
H28: =SUM(E28*G28) -> 0
H29: =SUM(E29*G29) -> 0
D30: Summe der Beseitigungskosten: | H30: =SUM(H20:H29) -> 0
B32: 3. Gerümpel, Hausrat und Sondermüll
H33: =SUM(E33*G33) -> 0
H34: =SUM(E34*G34) -> 0
H35: =SUM(E35*G35) -> 0
H36: =SUM(E36*G36) -> 0
H37: =SUM(E37*G37) -> 0
H38: =SUM(E38*G38) -> 0
H39: =SUM(E39*G39) -> 0
D40: Summe der Beseitigungskosten: | H40: =SUM(H33:H39) -> 0
A44: Die Ermittlung der Beseitigungskosten für bauliche Anlagen, Sondermüll, Gerümpel
A45: sowie nicht nutzbare Bepflanzung erfolgte unter Berücksichtigung der Richtlinien des
A46: Landesverbandes der Gartenfreunde e.V.
A50: Datum: xx.xx.xxxx | C50: Bezirksverband:

Sheet Bewertung Aufwuchs
A1: B. Bewertung des Aufwuchses Reg.-Nr.: | E1: ,
A3: Name des Unterpächters | D3: Kleingartenanlage | E3: Kleingarten-Nr.
A6: 0 | D6: 0 | E6: 0
A9: Anzahl | E9: Entschädigungswert
B10: m² | C10: Art | E10: Einzel | F10: Gesamt
A11: Stück | B11: lfdm | E11: € | F11: €
F12: =SUM(A12*E12) -> 0
F13: =SUM(A13*E13) -> 0
F14: =SUM(A14*E14) -> 0
F15: =SUM(A15*E15) -> 0
F16: =SUM(A16*E16) -> 0
F17: =SUM(A17*E17) -> 0
F18: =SUM(A18*E18) -> 0
F19: =SUM(A19*E19) -> 0
F20: =SUM(A20*E20) -> 0
F21: =SUM(A21*E21) -> 0
F22: =SUM(A22*E22) -> 0
F23: =SUM(A23*E23) -> 0
... F45: =SUM(A45*E45) -> 0
C46: *) Gem. Naturschutzgesetz § 29 Abs.5 ist es verboten,
C47: Bäume, Büsche oder Sträucher in der Zeit v. 1.März - 30.Sept. | F47: =SUM(A47*E47) -> 0
C48: zu fällen, zu roden oder auf andere Weise zu beseitigen. | F48: =SUM(A48*E48) -> 0
C50: -Nicht aufgeführter Aufwuchs ist ohne Bewertung
D51: Bewertung des Aufwuchses: | F51: =SUM(F12:F50) -> 0

Sheet Bewertung Außenanlagen
C1: C. Bewertung der Außenanlagen
A3: Anzahl | D3: Entschädigungswert
B4: m³ | C4: Art | D4: Einzel | E4: Gesamt
A5: Stück | B5: m²/lfdm | D5: € | E5: €
E8: =SUM(A8*D8) -> 0
E9: =SUM(A9*D9) -> 0
E10: =SUM(A10*D10) -> 0
E11: =SUM(A11*D11) -> 0
E12: =SUM(A12*D12) -> 0
E13: =SUM(A13*D13) -> 0
E14: =SUM(A14*D14) -> 0
E15: =SUM(A15*D15) -> 0
E16: =SUM(A16*D16) -> 0
E17: =SUM(A17*D17) -> 0
E18: =SUM(A18*D18) -> 0
E19: =SUM(A19*D19) -> 0
... E39: =SUM(A39*D39) -> 0
C40: **) 0,8m Spritzwasserumlauf ist berücksichtigt
C41: Bewertung der Außenanlagen: | E41: =SUM(E8:E40) -> 0
A43: Wertermittlung vom: | C43: xx.xx.xxxx
A45: ________________________
A46: Frau Mustermann

Sheet Beseitigungskosten
A2: Anlage 4 (Blatt 1) – Beseitigungskosten Bau/Außenanlagen
A3: Kleingartenanlage: | D3: =Formalien!$E$3 | H3: Parzelle/Weg:
A4: Name Unterpächter: | D4: =Formalien!$E$6 | G4: =IF(Formalien!$E$5="",Formalien!$E$4,Formalien!$E$4&" / "&Formalien!$E$5)
A7: Beseitigungskosten für nicht gestattete bauliche Anlagen oder nicht gestattete Bepflanzungen /
A8: Außenanlagen (einschließlich Folgekosten)
A10: 1. Zu entfernende Aufbauten laut Skizze Bau
B11: Bauteil/Gegenstand | F11: Menge | G11: ME | H11: Einzelpreis | J11: Faktor | K11: Summe | M11: bitumenhaltige Stoffe sind entsprechend der GefStoffV i.V.m. der TRGS 519 zu demontieren und zu entsorgen
A12: 1. | J12: 1 | K12: =(F12*H12*J12) | M12: bitumenhaltige Stoffe sind enstsprechend der GefStoffV i.V.m. der TRGS 519 zu demontieren und zu entsorgen.
J13: 1 | K13: =(F13*H13*J13) | M13: Entsorgung mit Nachweis
A14: 2. | J14: 1 | K14: =(F14*H14*J14) | M14: Entsorgung Sonderbaustoffe mit Nachweis
A15: 3. | J15: 1 | K15: =(F15*H15*J15) | M15: Entsorgung unterschiedlicher Gegenstände
A16: 4. | J16: 1 | K16: =(F16*H16*J16) | M16: nicht genutzte Baustoffe entfernen
A17: 5. | J17: 1 | K17: =(F17*H17*J17) | M17: Rückbau Anbau1 s. - Skizze Bau
A18: 6. | J18: 1 | K18: =(F18*H18*J18) | M18: Rückbau Keller s. - Skizze Bau
A19: 7. | J19: 1 | K19: =(F19*H19*J19)
A20: 8. | J20: 1 | K20: =(F20*H20*J20) | M20: Rückbau LVP komplett Ü1 ohne Bodenplatte s. -Skizze Bau
A21: 9. | J21: 1 | K21: =(F21*H21*J21) | M21: Sat.- Antenne entfernen
A22: 10. | J22: 1 | K22: =(F22*H22*J22) | M22: Schornsteinmauerwerk fachgerecht entsorgen.
A23: 11. | J23: 1 | K23: =(F23*H23*J23) | M23: Sondermüll mit Nachweis entfernen
A24: 12. | G24: Summe: | K24: =SUM(K12:K23) | M24: Unrat aus Baulichkeiten entfernen
A25: Begründung wenn Faktor über 100 % | M25: Well-/Ebenasbest ist Sondermüll, es ist enstsprechend der GefStoffV i.V.m. der TRGS 519 zu demontieren und zu entsorgen.
M29: Aussenhecke auf zul. Höhe (1,80m) schneiden
M30: Beetflächen auf 10% Parzellenfläche erhöhen
A32: 2. Zu entfernene Außenanlagen laut Skizze Außenanlagen-Aufwuchs | M32: Hecke auf zul. Höhe (1,25m) schneiden
F33: Menge | G33: ME | H33: Einzelpreis | J33: Faktor | K33: Summe | M33: Hecke lt. Skizze entfernen
A34: 1. | J34: 1 | K34: =(F34*H34*J34) | M34: nicht genutzte Baustoffe entfernen
A35: 2. | J35: 1 | K35: =(F35*H35*J35) | M35: Pool entfernen und Mutterboden auffüllen
A36: 3. | J36: 1 | K36: =(F36*H36*J36) | M36: Rückbau versiegelte Fläche (AA)
A37: 4. | J37: 1 | K37: =(F37*H37*J37) | M37: Spielgeräte beseitigen
A38: 5. | J38: 1 | K38: =(F38*H38*J38) | M38: Verwilderung beseitigen | N38: 1
A39: 6. | J39: 1 | K39: =(F39*H39*J39) | M39: Wiederherstellung kleing. Nutzung
A40: 7. | J40: 1 | K40: =(F40*H40*J40) | M40: Wurzelstock entfernen (roden)
A41: 8. | J41: 1 | K41: =(F41*H41*J41) | M41: Zweites Gartentor/-Tür entfernen, Zaunfeld einsetzen
A42: 9. | J42: 1 | K42: =(F42*H42*J42)
A43: 9. | J43: 1 | K43: =(F43*H43*J43)
A44: 10. | J44: 1 | K44: =(F44*H44*J44)
J45: Summe: | K45: =SUM(K34:K44)
A46: In der Zeit vom 1.März bis 30.Sepzember eines jeden Jahres dürfen aus Gründen des Naturschutzes, insbesondere des
A47: Vogelschutzes, keine Bäume sowie Gehölze entfernt werden.
A48: Pflegemaßnahmen sind soweit genehmigt oder genehmigungsfrei in moderatem Umfang möglich.
A49: Bei Fäll- und Schnittmaßnahmen dürfen Brut- oder Lebensstätten weder beeinträchtigt noch zerstört werden.
A50: Auf das Bundesnaturschutz- sowie das Berliner Naturschutzgesetz in ihren jeweils geltenden Fassungen wird hingewiesen.
A51: Hecken auf und an der Parzelle sind grundsätzlich ganzjährig auf eine Höhe von 1,25 m zu halten.
A53: Begründung wenn Faktor über 100 %
A60: Berlin, den | D60: =Formalien!$E$15 | E60: Wertermittler: | G60: =Formalien!$E$12 | I60: / | J60: =Formalien!$E$13
K61: Seite 7

Sheet Skizze Bau
A1: Skizze – Baulichkeiten
A2: Kleingartenanlage: | D2: =Formalien!$E$3 -> 0 | F2: Parzelle: | G2: =Formalien!$E$4 -> 0
A3: Parzellenfläche lt. Vertrag: | D3: =Formalien!$E$16 -> 0 | F3: =Formalien!$E$5 -> 0
A4: Name des Unterpächters: | D4: =Formalien!$E$6 -> 0
A50: Berlin, den | C50: =Formalien!$E$15 -> 0 | D50: Wertermittler: | E50: =Formalien!$E$12 -> 0

Sheet Skizze Außenanlage-Aufwuchs
A1: Skizze – Außenanlagen und Aufwuchs
A2: Kleingartenanlage: | D2: =Formalien!$E$3 -> 0 | F2: Parzelle: | G2: =Formalien!$E$4 -> 0
A3: Parzellenfläche lt. Vertrag: | D3: =Formalien!$E$16 -> 0 | F3: =Formalien!$E$5 -> 0
A4: Name des Unterpächters: | D4: =Formalien!$E$6 -> 0
A50: Berlin, den | C50: =Formalien!$E$15 -> 0 | D50: Wertermittler: | E50: =Formalien!$E$13 -> 0

Sheet Abkürzungsverzeichnis
A1: Abkürzungen
A2: Vertrag:
B3: UP | C3: Unterpächter
B4: UPV | C4: Unterpachtvertrag
B5: BV | C5: Bezirksverband (hier Gartenfreunde Pankow e.V.)
B7: Gfrd. | C7: Gartenfreund
B8: Gfrdn | C8: Gartenfreundin
B9: Gfrde | C9: Gartenfreunde
B11: KleingN | C11: Kleingärtnerische Nutzung im Sinne der Gartenordnung
B12: RiLW | C12: Richtlinie zur Wertermittlung von Kleingartenparzellen
C13: (hier des Landesverbandes Berlin)
B14: PW | C14: Pächterwechsel
A17: Baulichkeiten, Baumaterialien und Außenanlagen:
B18: A | C18: Anbau (A1 = Anbau 1; A2 = Anbau 2 usw.)
B19: ASG | C19: Abwassersammelgrube
B20: BG | C20: Baugenehmigung
B21: EA | C21: Elektroanschluss
B22: EZ | C22: Elektrozähler
B23: FI | C23: Fehlerstrom
B24: FOK | C24: Fußbodenoberkante
B25: GFP | C25: Glasfaserverstärktes Polyester
B26: GWH | C26: Gewächshaus
B27: HW | C27: Hauswasseranlage
B28: KST | C28: Kunststoff
B29: L | C29: Laube
... B45: zul. | C45: zulässig (im Sinne der Richtlinien)
C47: Bauklasse "U" ist keine Bauklasse im Sinne der Baubewertung. Sie gibt nur an,
C48: dass es sich um eine überdachte Fläche handelt.

Sheet Tabelle1
A1: Restnutzungstabelle | B1: Bauklasse: | C1: I | D1: II+III | E1: IV | F1: 0
A2: "RN2020" | B2: Spalte 1 | C2: 2 | D2: 3 | E2: 4 | F2: 5
A3: Restnutzungsjahre | B3: 0 | C3: 100 | D3: 100 | E3: 100 | F3: 0 | I3: Kleingärtnerische Nutzung
B4: 1 | C4: 98 | D4: 98 | E4: 98 | F4: 0 | I4: Anlage II | J4: F39
B5: 2 | C5: 96 | D5: 96 | E5: 96 | F5: =-I10
B6: 3 | C6: 94 | D6: 94 | E6: 94 | F6: 0 | I6: ausreichend
A7: nelke | B7: 4 | C7: 92 | D7: 92 | E7: 92 | F7: 0 | I7: fehlt ganz
B8: 5 | C8: 90 | D8: 90 | E8: 90 | F8: 0 | I8: nur teilweise
B9: 6 | C9: 89.8 | D9: 89 | E9: 86.2 | F9: 0
B10: 7 | C10: 89.6 | D10: 88 | E10: 82.4 | F10: 0
B11: 8 | C11: 89.3 | D11: 87 | E11: 78.6 | F11: 0 | I11: ungeprüft
B12: 9 | C12: 88.9 | D12: 86 | E12: 74.8 | F12: 0 | I12: Die Anlage wurde nicht geprüft. Die Entschädigung erfolgt nur dann, wenn der neue Unterpächter die Ordnungsmäßigkeit der Anlage bei Übergabe schriftlich bestätigt.
B13: 10 | C13: 88.5 | D13: 85 | E13: 71 | F13: 0
B14: 11 | C14: 88.2 | D14: 82.2 | E14: 67.6 | F14: 0
B15: 12 | C15: 86.4 | D15: 79.4 | E15: 64.2 | F15: 0
B16: 13 | C16: 84.6 | D16: 76.6 | E16: 60.8 | F16: 0
B17: 14 | C17: 82.8 | D17: 73.8 | E17: 57.4 | F17: 0
B18: 15 | C18: 81 | D18: 71 | E18: 54 | F18: 0
B19: 16 | C19: 79 | D19: 68.8 | E19: 51.2 | F19: 0
B20: 17 | C20: 77 | D20: 66.6 | E20: 48.4 | F20: 0
B21: 18 | C21: 75 | D21: 64.4 | E21: 45.6 | F21: 0
B22: 19 | C22: 73 | D22: 62.2 | E22: 42.8 | F22: 0
B23: 20 | C23: 71 | D23: 60 | E23: 40 | F23: 0
B24: 21 | C24: 69.2 | D24: 57.8 | E24: 37.8 | F24: 0
... B43: 40 | C43: 40 | D43: 26 | E43: 10 | F43: 0
B44: 41 | C44: 38.8 | D44: 25 | F44: 0
B45: 42 | C45: 37.6 | D45: 24 | F45: 0
B46: 43 | C46: 36.4 | D46: 23 | F46: 0
B47: 44 | C47: 35.2 | D47: 22 | F47: 0
B48: 45 | C48: 34 | D48: 21 | F48: 0
B49: 46 | C49: 33 | D49: 20.4 | F49: 0
B50: 47 | C50: 32 | D50: 19.8 | F50: 0
B51: 48 | C51: 31 | D51: 19.2 | F51: 0
B52: 49 | C52: 30 | D52: 18.6 | F52: 0 | J52: Spalte 1 | K52: 2 | L52: 3 | M52: 4 | N52: 5
B53: 50 | C53: 29 | D53: 18 | F53: 0 | J53: Bezeichnung | K53: Bauklasse | L53: NHK | M53: Abriss | N53: Altersabzug Spalte
B54: 51 | C54: 28.2 | D54: 17.5 | F54: 0 | I54: uwe | J54: Blockhaus 3,01 - 4,99 cm | K54: IV.2 | L54: 325 | N54: 4
B55: 52 | C55: 27.4 | D55: 17 | F55: 0 | J55: Blockhaus 6,00 - 7,49 cm | K55: III.1 | L55: 420 | N55: 3
B56: 53 | C56: 26.6 | D56: 16.5 | F56: 0 | J56: Blockhaus 7,50 - 8,99 cm | K56: III.2 | L56: 555 | N56: 3
B57: 54 | C57: 25.8 | D57: 16 | F57: 0 | J57: Blockhaus ab 5,00 cm | K57: IV.3 | L57: 420 | N57: 4
B58: 55 | C58: 25 | D58: 15.5 | F58: 0 | J58: Blockhaus ab 9,0 cm | K58: III.3 | L58: 672 | N58: 3
B59: 56 | C59: 24.2 | D59: 14.4 | F59: 0 | J59: Blockhaus bis 3,00 cm | K59: IV.1 | L59: 265 | N59: 4
B60: 57 | C60: 23.4 | D60: 13.3 | F60: 0 | J60: Doppelt Holz 10,01 - 14,99 cm | K60: III.1 | L60: 420 | N60: 3
B61: 58 | C61: 22.6 | D61: 12.2 | F61: 0 | J61: Doppelt Holz 15,00 - 19,99 cm | K61: III.2 | L61: 555 | N61: 3
B62: 59 | C62: 21.8 | D62: 11.1 | F62: 0 | J62: Doppelt Holz ab 20,00 cm | K62: III.3 | L62: 672 | N62: 3
B63: 60 | C63: 21 | D63: 10 | F63: 0 | J63: Doppelwand 4,01 - 8,00 cm | K63: IV.2 | L63: 325 | N63: 4
B64: 61 | C64: 20.3 | F64: 0 | J64: Doppelwand 8,01 - 10,00 cm | K64: IV.3 | L64: 420 | N64: 4
B65: 62 | C65: 19.6 | F65: 0 | J65: Doppelwand bis 4,00 cm | K65: IV.1 | L65: 265 | N65: 4
B66: 63 | C66: 18.9 | F66: 0 | J66: fehlt | K66: 0 | L66: 0 | N66: 5
B67: 64 | C67: 18.2 | F67: 0 | J67: I | M67: 180
B68: 65 | C68: 17.5 | F68: 0 | J68: II | M68: 180
B69: 66 | C69: 17.3 | F69: 0 | J69: III | M69: 150
B70: 67 | C70: 17.1 | F70: 0 | J70: IV | M70: 120
B71: 68 | C71: 16.9 | F71: 0 | J71: Stein 10,00 - 12,00 cm | K71: II.1 | L71: 350 | N71: 3
B72: 69 | C72: 16.7 | F72: 0 | J72: Stein 12,01 - 17,49 cm | K72: II.3 | L72: 490 | N72: 3
B73: 70 | C73: 16.5 | F73: 0 | J73: Stein 17,50 - 23,99 cm | K73: I.1 | L73: 515 | N73: 2
B74: 71 | C74: 16.3 | F74: 0 | J74: Stein 24,00 - 35,99 cm | K74: I.2 | L74: 595 | N74: 2
B75: 72 | C75: 16.1 | F75: 0 | J75: Stein ab 36,00 cm | K75: I.3 | L75: 704 | N75: 2
B76: 73 | C76: 15.9 | F76: 0
B77: 74 | C77: 15.7 | F77: 0
B78: 75 | C78: 15.5 | F78: 0
B79: 76 | C79: 14.4 | F79: 0
B80: 77 | C80: 13.3 | F80: 0
B81: 78 | C81: 12.2 | F81: 0
B82: 79 | C82: 11.1 | F82: 0
B83: 80 | C83: 10 | F83: 0
A87: Wertermittlung | J87: Stein 17,50 - 23,99 cm | K87: I.1
A88: BT | B88: =Baulichkeiten!$B$12 | C88: Bauklasse | D88: =VLOOKUP(D90,uwe,2) | E88: Spalte | F88: =VLOOKUP(D90,uwe,5) | H88: Restnutzungsjahre | I88: =Baulichkeiten!$I$13 | J88: Stein 24,00 - 35,99 cm | K88: I.2
J89: Stein ab 36,00 cm | K89: I.3
A90: NHK/m² | B90: =VLOOKUP(D90,uwe,3) | C90: Text | D90: =Baulichkeiten!$G$12 | H90: Abzug nach Tabelle | I90: =VLOOKUP(I88,nelke,F88) | J90: Stein 10,00 - 12,00 cm | K90: II.1
J91: Stein 12,01 - 17,49 cm | K91: II.3
J92: Blockhaus 6,00 - 7,49 cm | K92: III.1
A93: BT | B93: =Baulichkeiten!$B$21 | C93: Bauklasse | D93: =VLOOKUP(D95,uwe,2) | E93: Spalte | F93: =VLOOKUP(D95,uwe,5) | G93: Restnutzungsjahre | I93: =Baulichkeiten!$I$22 | J93: Blockhaus 7,50 - 8,99 cm | K93: III.2
J94: Blockhaus ab 9,0 cm | K94: III.3
A95: NHK/m² | B95: =VLOOKUP(D95,uwe,3) | C95: Text | D95: =Baulichkeiten!$G$21 | H95: Abzug nach Tabelle | I95: =VLOOKUP(I93,nelke,F93) | J95: Doppelt Holz 10,01 - 14,99 cm | K95: III.1
J96: Doppelt Holz 15,00 - 19,99 cm | K96: III.2
J97: Doppelt Holz ab 20,00 cm | K97: III.3
A98: BT | B98: =Baulichkeiten!$B$30 | C98: Bauklasse | D98: =VLOOKUP(D100,uwe,2) | E98: Spalte | F98: =VLOOKUP(D100,uwe,5) | G98: Restnutzungsjahre | I98: =Baulichkeiten!$I$31 | J98: Blockhaus bis 3,00 cm | K98: IV.1
J99: Blockhaus 3,01 - 4,99 cm | K99: IV.2
A100: Richtwert | B100: =VLOOKUP(D100,uwe,3) | C100: text | D100: =Baulichkeiten!$G$30 | H100: Abzug nach Tabelle | I100: =VLOOKUP(I98,nelke,F98) | J100: Blockhaus ab 5,00 cm | K100: IV.3
J101: Doppelwand bis 4,00 cm | K101: IV.1
J102: Doppelwand 4,01 - 8,00 cm | K102: IV.2
A103: BT | B103: =Baulichkeiten!$B$47 | C103: Bauklasse | D103: =IF(D105=J87,K87,IF(D105=J88,K88,IF(D105=J89,K89,IF(D105=J90,K90,IF(D105=J91,K91,IF(D105=J92,K92,IF(D105=J93,K93,IF(D105=J94,K94,IF(D105=J95,K95,IF(D105=J96,K96,IF(D105=J97,K97,IF(D105=J98,K98,IF(D105=J99,K99,IF(D105=J100,K100,IF(D105=J101,K101,IF(D105=J102,K102,IF(D105=J103,K103,IF(D105=J104,K104,IF(D105=J105,L105,IF(D105=J106,L106,IF(D105=J104,K104,IF(D105=J108,L108,IF(D105=J19:J109,L109))))))))))))))))))))))) | E103: Spalte | F103: =VLOOKUP(D105,uwe,5) | G103: Restnutzungsjahre | I103: =Baulichkeiten!$I$48 | J103: Doppelwand 8,01 - 10,00 cm | K103: IV.3
J104: fehlt | K104: 0
A105: Richtwert | B105: =VLOOKUP(D105,uwe,3) | C105: text | D105: =Baulichkeiten!$G$47 | H105: Abzug nach Tabelle | I105: =VLOOKUP(I103,nelke,F103)
C108: Blockhaus bis 3,00 cm
A110: Anl4 normal
A111: Abriss
A112: BT | B112: 1.1 | C112: Bauklasse | D112: =#REF! | E112: Spalte | F112: 6 | H112: von Anl.I >RN
C114: Abriss | D114: =VLOOKUP(D112,uwe,4) | H114: vonRN>Anl.I
H116: von Anl.IV>RN
A117: BT | B117: 1.2 | C117: Bauklasse | D117: =#REF! | E117: Spalte | F117: 6
H118: von RN>Anl.IV
C119: Abriss | D119: =VLOOKUP(D117,uwe,4)
A122: BT | B122: 1.3 | C122: Bauklasse | D122: =#REF! | E122: Spalte | F122: 6
C124: Abriss | D124: =VLOOKUP(D122,uwe,4)
B128: Bauklasse | C128: BKL.Beschreibung | E128: Spalte | F128: NHK/m² | G128: Abriss
B129: 1
B130: I | C130: I | G130: 180
B131: I.1 | C131: Stein 17,50 bis 23,99 cm | E131: 2 | F131: 515
B132: I.2 | C132: Stein 24,00 bis 35,99 cm | E132: 2 | F132: 595
...
